meganorm/__init__.py
meganorm/_version.py
meganorm/layouts/__init__.py
meganorm/layouts/layouts.py
meganorm/plots/__init__.py
meganorm/plots/plots.py
meganorm/src/__init__.py
meganorm/src/featureExtraction.py
meganorm/src/mainParallel.py
meganorm/src/preprocess.py
meganorm/src/psdParameterize.py
meganorm/utils/EEGlab.py
meganorm/utils/IO.py
meganorm/utils/__init__.py
meganorm/utils/freesurfer.py
meganorm/utils/nm.py
meganorm/utils/parallel.py
meganorm-0.1.1.dist-info/licenses/LICENSE
meganorm-0.1.1.dist-info/METADATA
meganorm-0.1.1.dist-info/WHEEL
meganorm-0.1.1.dist-info/top_level.txt
meganorm-0.1.1.dist-info/RECORD
