Metadata-Version: 2.4
Name: meganorm
Version: 0.1.1
Summary: A Python package for normative modeling on large-scale EEG and MEG data.
Home-page: https://github.com/ML4PNP/MEGaNorm
Author: Seyed Mostafa Kia, Mohammad Zamanzadeh, Ymke Verduyn
License: GNU GPLv3
Classifier: Programming Language :: Python :: 3
Classifier: License :: OSI Approved :: GNU General Public License v3 (GPLv3)
Classifier: Operating System :: OS Independent
Classifier: Intended Audience :: Science/Research
Classifier: Topic :: Scientific/Engineering :: Information Analysis
Requires-Python: >=3.12
License-File: LICENSE
Requires-Dist: numpy>=2.0
Requires-Dist: pandas>=2.0
Requires-Dist: scipy>=1.15.2
Requires-Dist: matplotlib>=3.10.1
Requires-Dist: seaborn>=0.13.2
Requires-Dist: plotly>=5.24.1
Requires-Dist: scikit_learn>=1.6.1
Requires-Dist: tqdm>=4.66.5
Requires-Dist: mne>=1.9.0
Requires-Dist: mne_bids>=0.16.0
Requires-Dist: mne_icalabel>=0.7.0
Requires-Dist: fooof>=1.1.0
Requires-Dist: pcntoolkit>=0.35.0
Dynamic: author
Dynamic: classifier
Dynamic: description
Dynamic: description-content-type
Dynamic: home-page
Dynamic: license
Dynamic: license-file
Dynamic: requires-dist
Dynamic: requires-python
Dynamic: summary
